{"name":"Houndoom","battleName":"Houndoom","slug":"houndoom","metadataCsv":"pokemon_champions_assets/metadata/Houndoom.csv","battleDataCsvs":[{"season":"Current","format":"Doubles","path":"pokemon_champions_assets/battle_data/Doubles/Houndoom.csv"},{"season":"Current","format":"Singles","path":"pokemon_champions_assets/battle_data/Singles/Houndoom.csv"}],"learnableMoveNames":["Beat Up","Bite","Body Slam","Burning Jealousy","Comeuppance","Counter","Crunch","Dark Pulse","Destiny Bond","Double-Edge","Endeavor","Endure","Facade","Feint","Fire Blast","Fire Fang","Fire Spin","Flame Charge","Flamethrower","Flare Blitz","Foul Play","Giga Impact","Heat Wave","Helping Hand","Howl","Hyper Beam","Hyper Voice","Inferno","Iron Tail","Lash Out","Mud Shot","Mud-Slap","Nasty Plot","Overheat","Pain Split","Payback","Protect","Psychic Fangs","Rain Dance","Rest","Reversal","Roar","Round","Scary Face","Scorching Sands","Shadow Ball","Sleep Talk","Sludge Bomb","Snarl","Snore","Solar Beam","Spite","Substitute","Sucker Punch","Sunny Day","Super Fang","Swagger","Taunt","Temper Flare","Thief","Throat Chop","Thunder Fang","Torment","Toxic","Trailblaze","Uproar","Will-O-Wisp"],"summary":{"dex":null,"sprite":"pokemon_champions_assets/pokemon/Houndoom.png","types":["Dark","Fire"],"primary":{"pokemon_name":"Houndoom","title":"Houndoom","dex_number":null,"base_dex_url":"","image_path":"pokemon_champions_assets/pokemon/Houndoom.png","form_name":"Houndoom","saved_name":"Houndoom","slug":"houndoom","form_kind":"Base","types":["Dark","Fire"],"types_raw":"Dark/Fire","abilities":"Early Bird|Flash Fire|Unnerve","hidden_ability":"","hp":150,"attack":110,"defense":70,"sp_attack":130,"sp_defense":100,"speed":115,"base_stat_total":675},"forms":[{"pokemon_name":"Houndoom","title":"Houndoom","dex_number":null,"base_dex_url":"","image_path":"pokemon_champions_assets/pokemon/Houndoom.png","form_name":"Houndoom","saved_name":"Houndoom","slug":"houndoom","form_kind":"Base","types":["Dark","Fire"],"types_raw":"Dark/Fire","abilities":"Early Bird|Flash Fire|Unnerve","hidden_ability":"","hp":150,"attack":110,"defense":70,"sp_attack":130,"sp_defense":100,"speed":115,"base_stat_total":675},{"pokemon_name":"Houndoom","title":"Houndoom [Mega Houndoom]","dex_number":null,"base_dex_url":"","image_path":"pokemon_champions_assets/pokemon/Mega Houndoom.png","form_name":"Mega Houndoom","saved_name":"Mega Houndoom","slug":"mega-houndoom","form_kind":"Mega","types":["Dark","Fire"],"types_raw":"Dark/Fire","abilities":"Solar Power","hidden_ability":"","hp":150,"attack":110,"defense":110,"sp_attack":160,"sp_defense":110,"speed":135,"base_stat_total":775}],"baseStats":{"hp":150,"attack":110,"defense":70,"sp_attack":130,"sp_defense":100,"speed":115},"baseStatTotal":675,"battleSummary":{"Current":{"Doubles":{"top":{"move":{"pokemon":"Houndoom","column_position":181,"position":181,"category":"move","rank":1,"name":"Protect","percentage":"87.5%","percentage_value":87.5,"stat_up":"","stat_down":""},"held_item":{"pokemon":"Houndoom","column_position":181,"position":181,"category":"held_item","rank":1,"name":"Houndoominite","percentage":"76.4%","percentage_value":76.4,"stat_up":"","stat_down":""},"teammate":{"pokemon":"Houndoom","column_position":181,"position":181,"category":"teammate","rank":1,"name":"Whimsicott","percentage":"","percentage_value":null,"stat_up":"","stat_down":""},"stat_alignment":{"pokemon":"Houndoom","column_position":181,"position":181,"category":"stat_alignment","rank":1,"name":"Timid","percentage":"68.7%","percentage_value":68.7,"stat_up":"Speed","stat_down":"Attack"},"stat_points":{"pokemon":"Houndoom","column_position":181,"position":181,"category":"stat_points","rank":1,"name":"","percentage":"46.2%","percentage_value":46.2,"stat_up":"","stat_down":"","hp_points":2,"attack_points":0,"defense_points":0,"sp_atk_points":32,"sp_def_points":0,"speed_points":32},"ability":{"pokemon":"Houndoom","column_position":181,"position":181,"category":"ability","rank":1,"name":"Flash Fire","percentage":"84.7%","percentage_value":84.7,"stat_up":"","stat_down":""}},"values":{"move":["Protect","Heat Wave","Dark Pulse","Solar Beam","Nasty Plot","Snarl","Flamethrower","Scorching Sands","Sucker Punch","Sludge Bomb"],"held_item":["Houndoominite","Focus Sash","Life Orb","Charcoal","Choice Scarf","Black Glasses","Chople Berry","Expert Belt","Quick Claw","Passho Berry"],"teammate":["Whimsicott","Garchomp","Torkoal","Staraptor","Basculegion Male","Sableye","Farigiraf","Ninetales","Sinistcha","Venusaur"],"stat_alignment":["Timid","Modest","Hasty","Mild","Calm","Quiet","Jolly","Bold","Gentle","Serious"],"stat_points":["HP 2 / Atk 0 / Def 0 / SpA 32 / SpD 0 / Spe 32","HP 0 / Atk 0 / Def 2 / SpA 32 / SpD 0 / Spe 32","HP 0 / Atk 0 / Def 0 / SpA 32 / SpD 2 / Spe 32","HP 1 / Atk 0 / Def 1 / SpA 32 / SpD 0 / Spe 32","HP 1 / Atk 1 / Def 0 / SpA 32 / SpD 0 / Spe 32","HP 0 / Atk 2 / Def 0 / SpA 32 / SpD 0 / Spe 32","HP 0 / Atk 0 / Def 0 / SpA 32 / SpD 0 / Spe 32","HP 0 / Atk 0 / Def 1 / SpA 32 / SpD 1 / Spe 32","HP 15 / Atk 0 / Def 0 / SpA 20 / SpD 0 / Spe 31","HP 1 / Atk 0 / Def 8 / SpA 25 / SpD 12 / Spe 20","HP 23 / Atk 0 / Def 0 / SpA 21 / SpD 0 / Spe 22","HP 32 / Atk 0 / Def 0 / SpA 32 / SpD 0 / Spe 1"],"ability":["Flash Fire","Unnerve","Early Bird"]},"rows":[{"pokemon":"Houndoom","column_position":181,"position":181,"category":"move","rank":1,"name":"Protect","percentage":"87.5%","percentage_value":87.5,"stat_up":"","stat_down":""},{"pokemon":"Houndoom","column_position":181,"position":181,"category":"move","rank":2,"name":"Heat Wave","percentage":"85.0%","percentage_value":85,"stat_up":"","stat_down":""},{"pokemon":"Houndoom","column_position":181,"position":181,"category":"move","rank":3,"name":"Dark Pulse","percentage":"82.3%","percentage_value":82.3,"stat_up":"","stat_down":""},{"pokemon":"Houndoom","column_position":181,"position":181,"category":"move","rank":4,"name":"Solar Beam","percentage":"38.7%","percentage_value":38.7,"stat_up":"","stat_down":""},{"pokemon":"Houndoom","column_position":181,"position":181,"category":"move","rank":5,"name":"Nasty Plot","percentage":"15.5%","percentage_value":15.5,"stat_up":"","stat_down":""},{"pokemon":"Houndoom","column_position":181,"position":181,"category":"move","rank":6,"name":"Snarl","percentage":"14.0%","percentage_value":14,"stat_up":"","stat_down":""},{"pokemon":"Houndoom","column_position":181,"position":181,"category":"move","rank":7,"name":"Flamethrower","percentage":"12.4%","percentage_value":12.4,"stat_up":"","stat_down":""},{"pokemon":"Houndoom","column_position":181,"position":181,"category":"move","rank":8,"name":"Scorching Sands","percentage":"11.8%","percentage_value":11.8,"stat_up":"","stat_down":""},{"pokemon":"Houndoom","column_position":181,"position":181,"category":"move","rank":9,"name":"Sucker Punch","percentage":"9.4%","percentage_value":9.4,"stat_up":"","stat_down":""},{"pokemon":"Houndoom","column_position":181,"position":181,"category":"move","rank":10,"name":"Sludge Bomb","percentage":"0.3%","percentage_value":0.3,"stat_up":"","stat_down":""},{"pokemon":"Houndoom","column_position":181,"position":181,"category":"held_item","rank":1,"name":"Houndoominite","percentage":"76.4%","percentage_value":76.4,"stat_up":"","stat_down":""},{"pokemon":"Houndoom","column_position":181,"position":181,"category":"held_item","rank":2,"name":"Focus Sash","percentage":"12.2%","percentage_value":12.2,"stat_up":"","stat_down":""},{"pokemon":"Houndoom","column_position":181,"position":181,"category":"held_item","rank":3,"name":"Life Orb","percentage":"2.5%","percentage_value":2.5,"stat_up":"","stat_down":""},{"pokemon":"Houndoom","column_position":181,"position":181,"category":"held_item","rank":4,"name":"Charcoal","percentage":"2.2%","percentage_value":2.2,"stat_up":"","stat_down":""},{"pokemon":"Houndoom","column_position":181,"position":181,"category":"held_item","rank":5,"name":"Choice Scarf","percentage":"1.9%","percentage_value":1.9,"stat_up":"","stat_down":""},{"pokemon":"Houndoom","column_position":181,"position":181,"category":"held_item","rank":6,"name":"Black Glasses","percentage":"1.6%","percentage_value":1.6,"stat_up":"","stat_down":""},{"pokemon":"Houndoom","column_position":181,"position":181,"category":"held_item","rank":7,"name":"Chople Berry","percentage":"0.4%","percentage_value":0.4,"stat_up":"","stat_down":""},{"pokemon":"Houndoom","column_position":181,"position":181,"category":"held_item","rank":8,"name":"Expert Belt","percentage":"0.3%","percentage_value":0.3,"stat_up":"","stat_down":""},{"pokemon":"Houndoom","column_position":181,"position":181,"category":"held_item","rank":9,"name":"Quick Claw","percentage":"0.3%","percentage_value":0.3,"stat_up":"","stat_down":""},{"pokemon":"Houndoom","column_position":181,"position":181,"category":"held_item","rank":10,"name":"Passho Berry","percentage":"0.2%","percentage_value":0.2,"stat_up":"","stat_down":""},{"pokemon":"Houndoom","column_position":181,"position":181,"category":"teammate","rank":1,"name":"Whimsicott","percentage":"","percentage_value":null,"stat_up":"","stat_down":""},{"pokemon":"Houndoom","column_position":181,"position":181,"category":"teammate","rank":2,"name":"Garchomp","percentage":"","percentage_value":null,"stat_up":"","stat_down":""},{"pokemon":"Houndoom","column_position":181,"position":181,"category":"teammate","rank":3,"name":"Torkoal","percentage":"","percentage_value":null,"stat_up":"","stat_down":""},{"pokemon":"Houndoom","column_position":181,"position":181,"category":"teammate","rank":4,"name":"Staraptor","percentage":"","percentage_value":null,"stat_up":"","stat_down":""},{"pokemon":"Houndoom","column_position":181,"position":181,"category":"teammate","rank":5,"name":"Basculegion Male","percentage":"","percentage_value":null,"stat_up":"","stat_down":""},{"pokemon":"Houndoom","column_position":181,"position":181,"category":"teammate","rank":6,"name":"Sableye","percentage":"","percentage_value":null,"stat_up":"","stat_down":""},{"pokemon":"Houndoom","column_position":181,"position":181,"category":"teammate","rank":7,"name":"Farigiraf","percentage":"","percentage_value":null,"stat_up":"","stat_down":""},{"pokemon":"Houndoom","column_position":181,"position":181,"category":"teammate","rank":8,"name":"Ninetales","percentage":"","percentage_value":null,"stat_up":"","stat_down":""},{"pokemon":"Houndoom","column_position":181,"position":181,"category":"teammate","rank":9,"name":"Sinistcha","percentage":"","percentage_value":null,"stat_up":"","stat_down":""},{"pokemon":"Houndoom","column_position":181,"position":181,"category":"teammate","rank":10,"name":"Venusaur","percentage":"","percentage_value":null,"stat_up":"","stat_down":""},{"pokemon":"Houndoom","column_position":181,"position":181,"category":"stat_alignment","rank":1,"name":"Timid","percentage":"68.7%","percentage_value":68.7,"stat_up":"Speed","stat_down":"Attack"},{"pokemon":"Houndoom","column_position":181,"position":181,"category":"stat_alignment","rank":2,"name":"Modest","percentage":"18.3%","percentage_value":18.3,"stat_up":"Sp. Atk","stat_down":"Attack"},{"pokemon":"Houndoom","column_position":181,"position":181,"category":"stat_alignment","rank":3,"name":"Hasty","percentage":"7.3%","percentage_value":7.3,"stat_up":"Speed","stat_down":"Defense"},{"pokemon":"Houndoom","column_position":181,"position":181,"category":"stat_alignment","rank":4,"name":"Mild","percentage":"2.3%","percentage_value":2.3,"stat_up":"Sp. Atk","stat_down":"Defense"},{"pokemon":"Houndoom","column_position":181,"position":181,"category":"stat_alignment","rank":5,"name":"Calm","percentage":"1.6%","percentage_value":1.6,"stat_up":"Sp. Def","stat_down":"Attack"},{"pokemon":"Houndoom","column_position":181,"position":181,"category":"stat_alignment","rank":6,"name":"Quiet","percentage":"0.6%","percentage_value":0.6,"stat_up":"Sp. Atk","stat_down":"Speed"},{"pokemon":"Houndoom","column_position":181,"position":181,"category":"stat_alignment","rank":7,"name":"Jolly","percentage":"0.3%","percentage_value":0.3,"stat_up":"Speed","stat_down":"Sp. Atk"},{"pokemon":"Houndoom","column_position":181,"position":181,"category":"stat_alignment","rank":8,"name":"Bold","percentage":"0.2%","percentage_value":0.2,"stat_up":"Defense","stat_down":"Attack"},{"pokemon":"Houndoom","column_position":181,"position":181,"category":"stat_alignment","rank":9,"name":"Gentle","percentage":"0.2%","percentage_value":0.2,"stat_up":"Sp. Def","stat_down":"Defense"},{"pokemon":"Houndoom","column_position":181,"position":181,"category":"stat_alignment","rank":10,"name":"Serious","percentage":"0.2%","percentage_value":0.2,"stat_up":"","stat_down":""},{"pokemon":"Houndoom","column_position":181,"position":181,"category":"stat_points","rank":1,"name":"","percentage":"46.2%","percentage_value":46.2,"stat_up":"","stat_down":"","hp_points":2,"attack_points":0,"defense_points":0,"sp_atk_points":32,"sp_def_points":0,"speed_points":32},{"pokemon":"Houndoom","column_position":181,"position":181,"category":"stat_points","rank":2,"name":"","percentage":"8.2%","percentage_value":8.2,"stat_up":"","stat_down":"","hp_points":0,"attack_points":0,"defense_points":2,"sp_atk_points":32,"sp_def_points":0,"speed_points":32},{"pokemon":"Houndoom","column_position":181,"position":181,"category":"stat_points","rank":3,"name":"","percentage":"5.9%","percentage_value":5.9,"stat_up":"","stat_down":"","hp_points":0,"attack_points":0,"defense_points":0,"sp_atk_points":32,"sp_def_points":2,"speed_points":32},{"pokemon":"Houndoom","column_position":181,"position":181,"category":"stat_points","rank":4,"name":"","percentage":"5.7%","percentage_value":5.7,"stat_up":"","stat_down":"","hp_points":1,"attack_points":0,"defense_points":1,"sp_atk_points":32,"sp_def_points":0,"speed_points":32},{"pokemon":"Houndoom","column_position":181,"position":181,"category":"stat_points","rank":5,"name":"","percentage":"4.7%","percentage_value":4.7,"stat_up":"","stat_down":"","hp_points":1,"attack_points":1,"defense_points":0,"sp_atk_points":32,"sp_def_points":0,"speed_points":32},{"pokemon":"Houndoom","column_position":181,"position":181,"category":"stat_points","rank":6,"name":"","percentage":"2.5%","percentage_value":2.5,"stat_up":"","stat_down":"","hp_points":0,"attack_points":2,"defense_points":0,"sp_atk_points":32,"sp_def_points":0,"speed_points":32},{"pokemon":"Houndoom","column_position":181,"position":181,"category":"stat_points","rank":7,"name":"","percentage":"2.4%","percentage_value":2.4,"stat_up":"","stat_down":"","hp_points":0,"attack_points":0,"defense_points":0,"sp_atk_points":32,"sp_def_points":0,"speed_points":32},{"pokemon":"Houndoom","column_position":181,"position":181,"category":"stat_points","rank":8,"name":"","percentage":"2.2%","percentage_value":2.2,"stat_up":"","stat_down":"","hp_points":0,"attack_points":0,"defense_points":1,"sp_atk_points":32,"sp_def_points":1,"speed_points":32},{"pokemon":"Houndoom","column_position":181,"position":181,"category":"stat_points","rank":9,"name":"","percentage":"1.7%","percentage_value":1.7,"stat_up":"","stat_down":"","hp_points":15,"attack_points":0,"defense_points":0,"sp_atk_points":20,"sp_def_points":0,"speed_points":31},{"pokemon":"Houndoom","column_position":181,"position":181,"category":"stat_points","rank":10,"name":"","percentage":"1.6%","percentage_value":1.6,"stat_up":"","stat_down":"","hp_points":1,"attack_points":0,"defense_points":8,"sp_atk_points":25,"sp_def_points":12,"speed_points":20},{"pokemon":"Houndoom","column_position":181,"position":181,"category":"stat_points","rank":11,"name":"","percentage":"1.0%","percentage_value":1,"stat_up":"","stat_down":"","hp_points":23,"attack_points":0,"defense_points":0,"sp_atk_points":21,"sp_def_points":0,"speed_points":22},{"pokemon":"Houndoom","column_position":181,"position":181,"category":"stat_points","rank":12,"name":"","percentage":"1.0%","percentage_value":1,"stat_up":"","stat_down":"","hp_points":32,"attack_points":0,"defense_points":0,"sp_atk_points":32,"sp_def_points":0,"speed_points":1},{"pokemon":"Houndoom","column_position":181,"position":181,"category":"ability","rank":1,"name":"Flash Fire","percentage":"84.7%","percentage_value":84.7,"stat_up":"","stat_down":""},{"pokemon":"Houndoom","column_position":181,"position":181,"category":"ability","rank":2,"name":"Unnerve","percentage":"10.7%","percentage_value":10.7,"stat_up":"","stat_down":""},{"pokemon":"Houndoom","column_position":181,"position":181,"category":"ability","rank":3,"name":"Early Bird","percentage":"4.6%","percentage_value":4.6,"stat_up":"","stat_down":""}]},"Singles":{"top":{"move":{"pokemon":"Houndoom","column_position":184,"position":184,"category":"move","rank":1,"name":"Dark Pulse","percentage":"78.6%","percentage_value":78.6,"stat_up":"","stat_down":""},"held_item":{"pokemon":"Houndoom","column_position":184,"position":184,"category":"held_item","rank":1,"name":"Houndoominite","percentage":"45.6%","percentage_value":45.6,"stat_up":"","stat_down":""},"teammate":{"pokemon":"Houndoom","column_position":184,"position":184,"category":"teammate","rank":1,"name":"Garchomp","percentage":"","percentage_value":null,"stat_up":"","stat_down":""},"stat_alignment":{"pokemon":"Houndoom","column_position":184,"position":184,"category":"stat_alignment","rank":1,"name":"Timid","percentage":"58.5%","percentage_value":58.5,"stat_up":"Speed","stat_down":"Attack"},"stat_points":{"pokemon":"Houndoom","column_position":184,"position":184,"category":"stat_points","rank":1,"name":"","percentage":"36.1%","percentage_value":36.1,"stat_up":"","stat_down":"","hp_points":2,"attack_points":0,"defense_points":0,"sp_atk_points":32,"sp_def_points":0,"speed_points":32},"ability":{"pokemon":"Houndoom","column_position":184,"position":184,"category":"ability","rank":1,"name":"Flash Fire","percentage":"88.2%","percentage_value":88.2,"stat_up":"","stat_down":""}},"values":{"move":["Dark Pulse","Flamethrower","Destiny Bond","Sucker Punch","Sludge Bomb","Counter","Overheat","Solar Beam","Fire Blast","Nasty Plot"],"held_item":["Houndoominite","Focus Sash","Choice Scarf","Life Orb","Charcoal","Sitrus Berry","White Herb","Leftovers","Wise Glasses","Black Glasses"],"teammate":["Garchomp","Meowscarada","Raichu","Staraptor","Mimikyu","Metagross","Corviknight","Torkoal","Gyarados","Archaludon"],"stat_alignment":["Timid","Modest","Hasty","Naive","Mild","Jolly","Quiet","Adamant","Rash","Brave"],"stat_points":["HP 2 / Atk 0 / Def 0 / SpA 32 / SpD 0 / Spe 32","HP 1 / Atk 0 / Def 1 / SpA 32 / SpD 0 / Spe 32","HP 0 / Atk 2 / Def 0 / SpA 32 / SpD 0 / Spe 32","HP 0 / Atk 0 / Def 0 / SpA 32 / SpD 0 / Spe 32","HP 1 / Atk 0 / Def 0 / SpA 32 / SpD 1 / Spe 32","HP 0 / Atk 0 / Def 2 / SpA 32 / SpD 0 / Spe 32","HP 0 / Atk 0 / Def 0 / SpA 32 / SpD 2 / Spe 32","HP 1 / Atk 1 / Def 0 / SpA 32 / SpD 0 / Spe 32","HP 1 / Atk 0 / Def 0 / SpA 32 / SpD 0 / Spe 32","HP 2 / Atk 32 / Def 0 / SpA 0 / SpD 0 / Spe 32","HP 30 / Atk 10 / Def 0 / SpA 26 / SpD 0 / Spe 0","HP 32 / Atk 0 / Def 0 / SpA 32 / SpD 2 / Spe 0"],"ability":["Flash Fire","Unnerve","Early Bird"]},"rows":[{"pokemon":"Houndoom","column_position":184,"position":184,"category":"move","rank":1,"name":"Dark Pulse","percentage":"78.6%","percentage_value":78.6,"stat_up":"","stat_down":""},{"pokemon":"Houndoom","column_position":184,"position":184,"category":"move","rank":2,"name":"Flamethrower","percentage":"59.9%","percentage_value":59.9,"stat_up":"","stat_down":""},{"pokemon":"Houndoom","column_position":184,"position":184,"category":"move","rank":3,"name":"Destiny Bond","percentage":"50.1%","percentage_value":50.1,"stat_up":"","stat_down":""},{"pokemon":"Houndoom","column_position":184,"position":184,"category":"move","rank":4,"name":"Sucker Punch","percentage":"34.2%","percentage_value":34.2,"stat_up":"","stat_down":""},{"pokemon":"Houndoom","column_position":184,"position":184,"category":"move","rank":5,"name":"Sludge Bomb","percentage":"25.3%","percentage_value":25.3,"stat_up":"","stat_down":""},{"pokemon":"Houndoom","column_position":184,"position":184,"category":"move","rank":6,"name":"Counter","percentage":"24.8%","percentage_value":24.8,"stat_up":"","stat_down":""},{"pokemon":"Houndoom","column_position":184,"position":184,"category":"move","rank":7,"name":"Overheat","percentage":"23.1%","percentage_value":23.1,"stat_up":"","stat_down":""},{"pokemon":"Houndoom","column_position":184,"position":184,"category":"move","rank":8,"name":"Solar Beam","percentage":"14.9%","percentage_value":14.9,"stat_up":"","stat_down":""},{"pokemon":"Houndoom","column_position":184,"position":184,"category":"move","rank":9,"name":"Fire Blast","percentage":"14.2%","percentage_value":14.2,"stat_up":"","stat_down":""},{"pokemon":"Houndoom","column_position":184,"position":184,"category":"move","rank":10,"name":"Nasty Plot","percentage":"13.5%","percentage_value":13.5,"stat_up":"","stat_down":""},{"pokemon":"Houndoom","column_position":184,"position":184,"category":"held_item","rank":1,"name":"Houndoominite","percentage":"45.6%","percentage_value":45.6,"stat_up":"","stat_down":""},{"pokemon":"Houndoom","column_position":184,"position":184,"category":"held_item","rank":2,"name":"Focus Sash","percentage":"40.2%","percentage_value":40.2,"stat_up":"","stat_down":""},{"pokemon":"Houndoom","column_position":184,"position":184,"category":"held_item","rank":3,"name":"Choice Scarf","percentage":"4.6%","percentage_value":4.6,"stat_up":"","stat_down":""},{"pokemon":"Houndoom","column_position":184,"position":184,"category":"held_item","rank":4,"name":"Life Orb","percentage":"2.5%","percentage_value":2.5,"stat_up":"","stat_down":""},{"pokemon":"Houndoom","column_position":184,"position":184,"category":"held_item","rank":5,"name":"Charcoal","percentage":"2.2%","percentage_value":2.2,"stat_up":"","stat_down":""},{"pokemon":"Houndoom","column_position":184,"position":184,"category":"held_item","rank":6,"name":"Sitrus Berry","percentage":"1.0%","percentage_value":1,"stat_up":"","stat_down":""},{"pokemon":"Houndoom","column_position":184,"position":184,"category":"held_item","rank":7,"name":"White Herb","percentage":"0.7%","percentage_value":0.7,"stat_up":"","stat_down":""},{"pokemon":"Houndoom","column_position":184,"position":184,"category":"held_item","rank":8,"name":"Leftovers","percentage":"0.5%","percentage_value":0.5,"stat_up":"","stat_down":""},{"pokemon":"Houndoom","column_position":184,"position":184,"category":"held_item","rank":9,"name":"Wise Glasses","percentage":"0.5%","percentage_value":0.5,"stat_up":"","stat_down":""},{"pokemon":"Houndoom","column_position":184,"position":184,"category":"held_item","rank":10,"name":"Black Glasses","percentage":"0.3%","percentage_value":0.3,"stat_up":"","stat_down":""},{"pokemon":"Houndoom","column_position":184,"position":184,"category":"teammate","rank":1,"name":"Garchomp","percentage":"","percentage_value":null,"stat_up":"","stat_down":""},{"pokemon":"Houndoom","column_position":184,"position":184,"category":"teammate","rank":2,"name":"Meowscarada","percentage":"","percentage_value":null,"stat_up":"","stat_down":""},{"pokemon":"Houndoom","column_position":184,"position":184,"category":"teammate","rank":3,"name":"Raichu","percentage":"","percentage_value":null,"stat_up":"","stat_down":""},{"pokemon":"Houndoom","column_position":184,"position":184,"category":"teammate","rank":4,"name":"Staraptor","percentage":"","percentage_value":null,"stat_up":"","stat_down":""},{"pokemon":"Houndoom","column_position":184,"position":184,"category":"teammate","rank":5,"name":"Mimikyu","percentage":"","percentage_value":null,"stat_up":"","stat_down":""},{"pokemon":"Houndoom","column_position":184,"position":184,"category":"teammate","rank":6,"name":"Metagross","percentage":"","percentage_value":null,"stat_up":"","stat_down":""},{"pokemon":"Houndoom","column_position":184,"position":184,"category":"teammate","rank":7,"name":"Corviknight","percentage":"","percentage_value":null,"stat_up":"","stat_down":""},{"pokemon":"Houndoom","column_position":184,"position":184,"category":"teammate","rank":8,"name":"Torkoal","percentage":"","percentage_value":null,"stat_up":"","stat_down":""},{"pokemon":"Houndoom","column_position":184,"position":184,"category":"teammate","rank":9,"name":"Gyarados","percentage":"","percentage_value":null,"stat_up":"","stat_down":""},{"pokemon":"Houndoom","column_position":184,"position":184,"category":"teammate","rank":10,"name":"Archaludon","percentage":"","percentage_value":null,"stat_up":"","stat_down":""},{"pokemon":"Houndoom","column_position":184,"position":184,"category":"stat_alignment","rank":1,"name":"Timid","percentage":"58.5%","percentage_value":58.5,"stat_up":"Speed","stat_down":"Attack"},{"pokemon":"Houndoom","column_position":184,"position":184,"category":"stat_alignment","rank":2,"name":"Modest","percentage":"15.7%","percentage_value":15.7,"stat_up":"Sp. Atk","stat_down":"Attack"},{"pokemon":"Houndoom","column_position":184,"position":184,"category":"stat_alignment","rank":3,"name":"Hasty","percentage":"10.8%","percentage_value":10.8,"stat_up":"Speed","stat_down":"Defense"},{"pokemon":"Houndoom","column_position":184,"position":184,"category":"stat_alignment","rank":4,"name":"Naive","percentage":"4.7%","percentage_value":4.7,"stat_up":"Speed","stat_down":"Sp. Def"},{"pokemon":"Houndoom","column_position":184,"position":184,"category":"stat_alignment","rank":5,"name":"Mild","percentage":"4.0%","percentage_value":4,"stat_up":"Sp. Atk","stat_down":"Defense"},{"pokemon":"Houndoom","column_position":184,"position":184,"category":"stat_alignment","rank":6,"name":"Jolly","percentage":"1.7%","percentage_value":1.7,"stat_up":"Speed","stat_down":"Sp. Atk"},{"pokemon":"Houndoom","column_position":184,"position":184,"category":"stat_alignment","rank":7,"name":"Quiet","percentage":"1.0%","percentage_value":1,"stat_up":"Sp. Atk","stat_down":"Speed"},{"pokemon":"Houndoom","column_position":184,"position":184,"category":"stat_alignment","rank":8,"name":"Adamant","percentage":"0.9%","percentage_value":0.9,"stat_up":"Attack","stat_down":"Sp. Atk"},{"pokemon":"Houndoom","column_position":184,"position":184,"category":"stat_alignment","rank":9,"name":"Rash","percentage":"0.6%","percentage_value":0.6,"stat_up":"Sp. Atk","stat_down":"Sp. Def"},{"pokemon":"Houndoom","column_position":184,"position":184,"category":"stat_alignment","rank":10,"name":"Brave","percentage":"0.6%","percentage_value":0.6,"stat_up":"Attack","stat_down":"Speed"},{"pokemon":"Houndoom","column_position":184,"position":184,"category":"stat_points","rank":1,"name":"","percentage":"36.1%","percentage_value":36.1,"stat_up":"","stat_down":"","hp_points":2,"attack_points":0,"defense_points":0,"sp_atk_points":32,"sp_def_points":0,"speed_points":32},{"pokemon":"Houndoom","column_position":184,"position":184,"category":"stat_points","rank":2,"name":"","percentage":"12.6%","percentage_value":12.6,"stat_up":"","stat_down":"","hp_points":1,"attack_points":0,"defense_points":1,"sp_atk_points":32,"sp_def_points":0,"speed_points":32},{"pokemon":"Houndoom","column_position":184,"position":184,"category":"stat_points","rank":3,"name":"","percentage":"5.7%","percentage_value":5.7,"stat_up":"","stat_down":"","hp_points":0,"attack_points":2,"defense_points":0,"sp_atk_points":32,"sp_def_points":0,"speed_points":32},{"pokemon":"Houndoom","column_position":184,"position":184,"category":"stat_points","rank":4,"name":"","percentage":"5.4%","percentage_value":5.4,"stat_up":"","stat_down":"","hp_points":0,"attack_points":0,"defense_points":0,"sp_atk_points":32,"sp_def_points":0,"speed_points":32},{"pokemon":"Houndoom","column_position":184,"position":184,"category":"stat_points","rank":5,"name":"","percentage":"5.2%","percentage_value":5.2,"stat_up":"","stat_down":"","hp_points":1,"attack_points":0,"defense_points":0,"sp_atk_points":32,"sp_def_points":1,"speed_points":32},{"pokemon":"Houndoom","column_position":184,"position":184,"category":"stat_points","rank":6,"name":"","percentage":"4.9%","percentage_value":4.9,"stat_up":"","stat_down":"","hp_points":0,"attack_points":0,"defense_points":2,"sp_atk_points":32,"sp_def_points":0,"speed_points":32},{"pokemon":"Houndoom","column_position":184,"position":184,"category":"stat_points","rank":7,"name":"","percentage":"4.9%","percentage_value":4.9,"stat_up":"","stat_down":"","hp_points":0,"attack_points":0,"defense_points":0,"sp_atk_points":32,"sp_def_points":2,"speed_points":32},{"pokemon":"Houndoom","column_position":184,"position":184,"category":"stat_points","rank":8,"name":"","percentage":"1.8%","percentage_value":1.8,"stat_up":"","stat_down":"","hp_points":1,"attack_points":1,"defense_points":0,"sp_atk_points":32,"sp_def_points":0,"speed_points":32},{"pokemon":"Houndoom","column_position":184,"position":184,"category":"stat_points","rank":9,"name":"","percentage":"1.3%","percentage_value":1.3,"stat_up":"","stat_down":"","hp_points":1,"attack_points":0,"defense_points":0,"sp_atk_points":32,"sp_def_points":0,"speed_points":32},{"pokemon":"Houndoom","column_position":184,"position":184,"category":"stat_points","rank":10,"name":"","percentage":"1.0%","percentage_value":1,"stat_up":"","stat_down":"","hp_points":2,"attack_points":32,"defense_points":0,"sp_atk_points":0,"sp_def_points":0,"speed_points":32},{"pokemon":"Houndoom","column_position":184,"position":184,"category":"stat_points","rank":11,"name":"","percentage":"0.8%","percentage_value":0.8,"stat_up":"","stat_down":"","hp_points":30,"attack_points":10,"defense_points":0,"sp_atk_points":26,"sp_def_points":0,"speed_points":0},{"pokemon":"Houndoom","column_position":184,"position":184,"category":"stat_points","rank":12,"name":"","percentage":"0.8%","percentage_value":0.8,"stat_up":"","stat_down":"","hp_points":32,"attack_points":0,"defense_points":0,"sp_atk_points":32,"sp_def_points":2,"speed_points":0},{"pokemon":"Houndoom","column_position":184,"position":184,"category":"ability","rank":1,"name":"Flash Fire","percentage":"88.2%","percentage_value":88.2,"stat_up":"","stat_down":""},{"pokemon":"Houndoom","column_position":184,"position":184,"category":"ability","rank":2,"name":"Unnerve","percentage":"6.9%","percentage_value":6.9,"stat_up":"","stat_down":""},{"pokemon":"Houndoom","column_position":184,"position":184,"category":"ability","rank":3,"name":"Early Bird","percentage":"4.8%","percentage_value":4.8,"stat_up":"","stat_down":""}]}}}}}
