{"name":"Sharpedo","battleName":"Sharpedo","slug":"sharpedo","showdownId":"sharpedo","showdownName":"Sharpedo","metadataCsv":"pokemon_champions_assets/metadata/Sharpedo.csv","battleDataCsvs":[{"season":"M4","format":"Doubles","path":"pokemon_champions_assets/battle_data/M4/16_07_2026/Doubles/Sharpedo.csv","date":"16_07_2026","daily":true},{"season":"M4","format":"Singles","path":"pokemon_champions_assets/battle_data/M4/16_07_2026/Singles/Sharpedo.csv","date":"16_07_2026","daily":true},{"season":"Current","format":"Singles","path":"pokemon_champions_assets/battle_data/Singles/Sharpedo.csv"},{"season":"Current","format":"Doubles","path":"pokemon_champions_assets/battle_data/Doubles/Sharpedo.csv"}],"learnableMoveNames":["Agility","Ancient Power","Aqua Jet","Assurance","Attract","Avalanche","Bite","Blizzard","Bounce","Brine","Bulldoze","Chilling Water","Close Combat","Crunch","Dark Pulse","Destiny Bond","Dive","Double-Edge","Earthquake","Endure","Facade","Flip Turn","Focus Energy","Giga Impact","Hail","Hydro Pump","Hyper Beam","Ice Beam","Ice Fang","Icy Wind","Liquidation","Night Slash","Payback","Poison Fang","Poison Jab","Protect","Psychic Fangs","Rain Dance","Rest","Retaliate","Rock Tomb","Round","Scald","Scale Shot","Scary Face","Screech","Sleep Talk","Snarl","Snore","Substitute","Surf","Swagger","Taunt","Thief","Thrash","Uproar","Water Pulse","Waterfall","Whirlpool","Zen Headbutt"],"summary":{"dex":null,"sprite":"pokemon_champions_assets/pokemon/Sharpedo.png","types":["Water","Dark"],"primary":{"pokemon_name":"Sharpedo","title":"Sharpedo","dex_number":null,"base_dex_url":"","image_path":"pokemon_champions_assets/pokemon/Sharpedo.png","form_name":"Sharpedo","saved_name":"Sharpedo","slug":"sharpedo","form_kind":"Base","types":["Water","Dark"],"types_raw":"Water/Dark","abilities":"Rough Skin|Speed Boost","hidden_ability":"","hp":145,"attack":140,"defense":60,"sp_attack":115,"sp_defense":60,"speed":115,"base_stat_total":635},"forms":[{"pokemon_name":"Sharpedo","title":"Sharpedo","dex_number":null,"base_dex_url":"","image_path":"pokemon_champions_assets/pokemon/Sharpedo.png","form_name":"Sharpedo","saved_name":"Sharpedo","slug":"sharpedo","form_kind":"Base","types":["Water","Dark"],"types_raw":"Water/Dark","abilities":"Rough Skin|Speed Boost","hidden_ability":"","hp":145,"attack":140,"defense":60,"sp_attack":115,"sp_defense":60,"speed":115,"base_stat_total":635},{"pokemon_name":"Sharpedo","title":"Sharpedo [Mega Sharpedo]","dex_number":null,"base_dex_url":"","image_path":"pokemon_champions_assets/pokemon/Mega Sharpedo.png","form_name":"Mega Sharpedo","saved_name":"Mega Sharpedo","slug":"mega-sharpedo","form_kind":"Mega","types":["Water","Dark"],"types_raw":"Water/Dark","abilities":"Strong Jaw","hidden_ability":"","hp":145,"attack":160,"defense":90,"sp_attack":130,"sp_defense":85,"speed":125,"base_stat_total":735}],"baseStats":{"hp":145,"attack":140,"defense":60,"sp_attack":115,"sp_defense":60,"speed":115},"baseStatTotal":635,"battleSummary":{"Current":{"Doubles":{"top":{"move":{"pokemon":"Sharpedo","column_position":185,"position":185,"category":"move","rank":1,"name":"Protect","percentage":"96.4%","percentage_value":96.4,"stat_up":"","stat_down":""},"held_item":{"pokemon":"Sharpedo","column_position":185,"position":185,"category":"held_item","rank":1,"name":"Sharpedonite","percentage":"17.0%","percentage_value":17,"stat_up":"","stat_down":""},"teammate":{"pokemon":"Sharpedo","column_position":185,"position":185,"category":"teammate","rank":1,"name":"Sneasler","percentage":"","percentage_value":null,"stat_up":"","stat_down":""},"stat_alignment":{"pokemon":"Sharpedo","column_position":185,"position":185,"category":"stat_alignment","rank":1,"name":"Adamant","percentage":"81.3%","percentage_value":81.3,"stat_up":"Attack","stat_down":"Sp. Atk"},"stat_points":{"pokemon":"Sharpedo","column_position":185,"position":185,"category":"stat_points","rank":1,"name":"","percentage":"65.0%","percentage_value":65,"stat_up":"","stat_down":"","hp_points":2,"attack_points":32,"defense_points":0,"sp_atk_points":0,"sp_def_points":0,"speed_points":32},"ability":{"pokemon":"Sharpedo","column_position":185,"position":185,"category":"ability","rank":1,"name":"Speed Boost","percentage":"98.9%","percentage_value":98.9,"stat_up":"","stat_down":""}},"values":{"move":["Protect","Crunch","Ice Fang","Psychic Fangs","Liquidation","Close Combat","Destiny Bond","Waterfall","Rock Tomb","Poison Fang"],"held_item":["Sharpedonite","Focus Sash","Life Orb","Black Glasses","Mystic Water","Scope Lens","Quick Claw","Expert Belt","Sitrus Berry","Lum Berry"],"teammate":["Sneasler","Talonflame","Whimsicott","Sylveon","Kingambit","Farigiraf","Raichu","Incineroar","Milotic","Garchomp"],"stat_alignment":["Adamant","Jolly","Naive","Timid","Hasty","Naughty","Lonely","Modest","Brave","Bashful"],"stat_points":["HP 2 / Atk 32 / Def 0 / SpA 0 / SpD 0 / Spe 32","HP 0 / Atk 32 / Def 2 / SpA 0 / SpD 0 / Spe 32","HP 0 / Atk 32 / Def 0 / SpA 0 / SpD 2 / Spe 32","HP 0 / Atk 32 / Def 4 / SpA 0 / SpD 0 / Spe 30","HP 15 / Atk 32 / Def 0 / SpA 0 / SpD 0 / Spe 19","HP 14 / Atk 32 / Def 0 / SpA 0 / SpD 0 / Spe 20","HP 27 / Atk 30 / Def 0 / SpA 0 / SpD 0 / Spe 9","HP 0 / Atk 32 / Def 17 / SpA 0 / SpD 0 / Spe 17"],"ability":["Speed Boost","Rough Skin"]},"rows":[{"pokemon":"Sharpedo","column_position":185,"position":185,"category":"move","rank":1,"name":"Protect","percentage":"96.4%","percentage_value":96.4,"stat_up":"","stat_down":""},{"pokemon":"Sharpedo","column_position":185,"position":185,"category":"move","rank":2,"name":"Crunch","percentage":"95.6%","percentage_value":95.6,"stat_up":"","stat_down":""},{"pokemon":"Sharpedo","column_position":185,"position":185,"category":"move","rank":3,"name":"Ice Fang","percentage":"60.5%","percentage_value":60.5,"stat_up":"","stat_down":""},{"pokemon":"Sharpedo","column_position":185,"position":185,"category":"move","rank":4,"name":"Psychic Fangs","percentage":"59.8%","percentage_value":59.8,"stat_up":"","stat_down":""},{"pokemon":"Sharpedo","column_position":185,"position":185,"category":"move","rank":5,"name":"Liquidation","percentage":"27.5%","percentage_value":27.5,"stat_up":"","stat_down":""},{"pokemon":"Sharpedo","column_position":185,"position":185,"category":"move","rank":6,"name":"Close Combat","percentage":"11.6%","percentage_value":11.6,"stat_up":"","stat_down":""},{"pokemon":"Sharpedo","column_position":185,"position":185,"category":"move","rank":7,"name":"Destiny Bond","percentage":"11.0%","percentage_value":11,"stat_up":"","stat_down":""},{"pokemon":"Sharpedo","column_position":185,"position":185,"category":"move","rank":8,"name":"Waterfall","percentage":"9.1%","percentage_value":9.1,"stat_up":"","stat_down":""},{"pokemon":"Sharpedo","column_position":185,"position":185,"category":"move","rank":9,"name":"Rock Tomb","percentage":"5.4%","percentage_value":5.4,"stat_up":"","stat_down":""},{"pokemon":"Sharpedo","column_position":185,"position":185,"category":"move","rank":10,"name":"Poison Fang","percentage":"4.8%","percentage_value":4.8,"stat_up":"","stat_down":""},{"pokemon":"Sharpedo","column_position":185,"position":185,"category":"held_item","rank":1,"name":"Sharpedonite","percentage":"17.0%","percentage_value":17,"stat_up":"","stat_down":""},{"pokemon":"Sharpedo","column_position":185,"position":185,"category":"held_item","rank":2,"name":"Focus Sash","percentage":"13.3%","percentage_value":13.3,"stat_up":"","stat_down":""},{"pokemon":"Sharpedo","column_position":185,"position":185,"category":"held_item","rank":3,"name":"Life Orb","percentage":"3.9%","percentage_value":3.9,"stat_up":"","stat_down":""},{"pokemon":"Sharpedo","column_position":185,"position":185,"category":"held_item","rank":4,"name":"Black Glasses","percentage":"0.9%","percentage_value":0.9,"stat_up":"","stat_down":""},{"pokemon":"Sharpedo","column_position":185,"position":185,"category":"held_item","rank":5,"name":"Mystic Water","percentage":"0.9%","percentage_value":0.9,"stat_up":"","stat_down":""},{"pokemon":"Sharpedo","column_position":185,"position":185,"category":"held_item","rank":6,"name":"Scope Lens","percentage":"0.8%","percentage_value":0.8,"stat_up":"","stat_down":""},{"pokemon":"Sharpedo","column_position":185,"position":185,"category":"held_item","rank":7,"name":"Quick Claw","percentage":"0.8%","percentage_value":0.8,"stat_up":"","stat_down":""},{"pokemon":"Sharpedo","column_position":185,"position":185,"category":"held_item","rank":8,"name":"Expert Belt","percentage":"0.7%","percentage_value":0.7,"stat_up":"","stat_down":""},{"pokemon":"Sharpedo","column_position":185,"position":185,"category":"held_item","rank":9,"name":"Sitrus Berry","percentage":"0.2%","percentage_value":0.2,"stat_up":"","stat_down":""},{"pokemon":"Sharpedo","column_position":185,"position":185,"category":"held_item","rank":10,"name":"Lum Berry","percentage":"0.2%","percentage_value":0.2,"stat_up":"","stat_down":""},{"pokemon":"Sharpedo","column_position":185,"position":185,"category":"teammate","rank":1,"name":"Sneasler","percentage":"","percentage_value":null,"stat_up":"","stat_down":""},{"pokemon":"Sharpedo","column_position":185,"position":185,"category":"teammate","rank":2,"name":"Talonflame","percentage":"","percentage_value":null,"stat_up":"","stat_down":""},{"pokemon":"Sharpedo","column_position":185,"position":185,"category":"teammate","rank":3,"name":"Whimsicott","percentage":"","percentage_value":null,"stat_up":"","stat_down":""},{"pokemon":"Sharpedo","column_position":185,"position":185,"category":"teammate","rank":4,"name":"Sylveon","percentage":"","percentage_value":null,"stat_up":"","stat_down":""},{"pokemon":"Sharpedo","column_position":185,"position":185,"category":"teammate","rank":5,"name":"Kingambit","percentage":"","percentage_value":null,"stat_up":"","stat_down":""},{"pokemon":"Sharpedo","column_position":185,"position":185,"category":"teammate","rank":6,"name":"Farigiraf","percentage":"","percentage_value":null,"stat_up":"","stat_down":""},{"pokemon":"Sharpedo","column_position":185,"position":185,"category":"teammate","rank":7,"name":"Raichu","percentage":"","percentage_value":null,"stat_up":"","stat_down":""},{"pokemon":"Sharpedo","column_position":185,"position":185,"category":"teammate","rank":8,"name":"Incineroar","percentage":"","percentage_value":null,"stat_up":"","stat_down":""},{"pokemon":"Sharpedo","column_position":185,"position":185,"category":"teammate","rank":9,"name":"Milotic","percentage":"","percentage_value":null,"stat_up":"","stat_down":""},{"pokemon":"Sharpedo","column_position":185,"position":185,"category":"teammate","rank":10,"name":"Garchomp","percentage":"","percentage_value":null,"stat_up":"","stat_down":""},{"pokemon":"Sharpedo","column_position":185,"position":185,"category":"stat_alignment","rank":1,"name":"Adamant","percentage":"81.3%","percentage_value":81.3,"stat_up":"Attack","stat_down":"Sp. Atk"},{"pokemon":"Sharpedo","column_position":185,"position":185,"category":"stat_alignment","rank":2,"name":"Jolly","percentage":"13.6%","percentage_value":13.6,"stat_up":"Speed","stat_down":"Sp. Atk"},{"pokemon":"Sharpedo","column_position":185,"position":185,"category":"stat_alignment","rank":3,"name":"Naive","percentage":"1.4%","percentage_value":1.4,"stat_up":"Speed","stat_down":"Sp. Def"},{"pokemon":"Sharpedo","column_position":185,"position":185,"category":"stat_alignment","rank":4,"name":"Timid","percentage":"1.2%","percentage_value":1.2,"stat_up":"Speed","stat_down":"Attack"},{"pokemon":"Sharpedo","column_position":185,"position":185,"category":"stat_alignment","rank":5,"name":"Hasty","percentage":"0.8%","percentage_value":0.8,"stat_up":"Speed","stat_down":"Defense"},{"pokemon":"Sharpedo","column_position":185,"position":185,"category":"stat_alignment","rank":6,"name":"Naughty","percentage":"0.6%","percentage_value":0.6,"stat_up":"Attack","stat_down":"Sp. Def"},{"pokemon":"Sharpedo","column_position":185,"position":185,"category":"stat_alignment","rank":7,"name":"Lonely","percentage":"0.4%","percentage_value":0.4,"stat_up":"Attack","stat_down":"Defense"},{"pokemon":"Sharpedo","column_position":185,"position":185,"category":"stat_alignment","rank":8,"name":"Modest","percentage":"0.2%","percentage_value":0.2,"stat_up":"Sp. Atk","stat_down":"Attack"},{"pokemon":"Sharpedo","column_position":185,"position":185,"category":"stat_alignment","rank":9,"name":"Brave","percentage":"0.2%","percentage_value":0.2,"stat_up":"Attack","stat_down":"Speed"},{"pokemon":"Sharpedo","column_position":185,"position":185,"category":"stat_alignment","rank":10,"name":"Bashful","percentage":"0.1%","percentage_value":0.1,"stat_up":"","stat_down":""},{"pokemon":"Sharpedo","column_position":185,"position":185,"category":"stat_points","rank":1,"name":"","percentage":"65.0%","percentage_value":65,"stat_up":"","stat_down":"","hp_points":2,"attack_points":32,"defense_points":0,"sp_atk_points":0,"sp_def_points":0,"speed_points":32},{"pokemon":"Sharpedo","column_position":185,"position":185,"category":"stat_points","rank":2,"name":"","percentage":"3.3%","percentage_value":3.3,"stat_up":"","stat_down":"","hp_points":0,"attack_points":32,"defense_points":2,"sp_atk_points":0,"sp_def_points":0,"speed_points":32},{"pokemon":"Sharpedo","column_position":185,"position":185,"category":"stat_points","rank":3,"name":"","percentage":"3.2%","percentage_value":3.2,"stat_up":"","stat_down":"","hp_points":0,"attack_points":32,"defense_points":0,"sp_atk_points":0,"sp_def_points":2,"speed_points":32},{"pokemon":"Sharpedo","column_position":185,"position":185,"category":"stat_points","rank":4,"name":"","percentage":"2.7%","percentage_value":2.7,"stat_up":"","stat_down":"","hp_points":0,"attack_points":32,"defense_points":4,"sp_atk_points":0,"sp_def_points":0,"speed_points":30},{"pokemon":"Sharpedo","column_position":185,"position":185,"category":"stat_points","rank":5,"name":"","percentage":"2.5%","percentage_value":2.5,"stat_up":"","stat_down":"","hp_points":15,"attack_points":32,"defense_points":0,"sp_atk_points":0,"sp_def_points":0,"speed_points":19},{"pokemon":"Sharpedo","column_position":185,"position":185,"category":"stat_points","rank":6,"name":"","percentage":"1.6%","percentage_value":1.6,"stat_up":"","stat_down":"","hp_points":14,"attack_points":32,"defense_points":0,"sp_atk_points":0,"sp_def_points":0,"speed_points":20},{"pokemon":"Sharpedo","column_position":185,"position":185,"category":"stat_points","rank":7,"name":"","percentage":"1.6%","percentage_value":1.6,"stat_up":"","stat_down":"","hp_points":27,"attack_points":30,"defense_points":0,"sp_atk_points":0,"sp_def_points":0,"speed_points":9},{"pokemon":"Sharpedo","column_position":185,"position":185,"category":"stat_points","rank":8,"name":"","percentage":"1.5%","percentage_value":1.5,"stat_up":"","stat_down":"","hp_points":0,"attack_points":32,"defense_points":17,"sp_atk_points":0,"sp_def_points":0,"speed_points":17},{"pokemon":"Sharpedo","column_position":185,"position":185,"category":"ability","rank":1,"name":"Speed Boost","percentage":"98.9%","percentage_value":98.9,"stat_up":"","stat_down":""},{"pokemon":"Sharpedo","column_position":185,"position":185,"category":"ability","rank":2,"name":"Rough Skin","percentage":"1.1%","percentage_value":1.1,"stat_up":"","stat_down":""}]},"Singles":{"top":{"move":{"pokemon":"Sharpedo","column_position":108,"position":108,"category":"move","rank":1,"name":"Protect","percentage":"83.6%","percentage_value":83.6,"stat_up":"","stat_down":""},"held_item":{"pokemon":"Sharpedo","column_position":108,"position":108,"category":"held_item","rank":1,"name":"Sharpedonite","percentage":"50.4%","percentage_value":50.4,"stat_up":"","stat_down":""},"teammate":{"pokemon":"Sharpedo","column_position":108,"position":108,"category":"teammate","rank":1,"name":"Garchomp","percentage":"","percentage_value":null,"stat_up":"","stat_down":""},"stat_alignment":{"pokemon":"Sharpedo","column_position":108,"position":108,"category":"stat_alignment","rank":1,"name":"Adamant","percentage":"60.9%","percentage_value":60.9,"stat_up":"Attack","stat_down":"Sp. Atk"},"stat_points":{"pokemon":"Sharpedo","column_position":108,"position":108,"category":"stat_points","rank":1,"name":"","percentage":"58.7%","percentage_value":58.7,"stat_up":"","stat_down":"","hp_points":2,"attack_points":32,"defense_points":0,"sp_atk_points":0,"sp_def_points":0,"speed_points":32},"ability":{"pokemon":"Sharpedo","column_position":108,"position":108,"category":"ability","rank":1,"name":"Speed Boost","percentage":"99.4%","percentage_value":99.4,"stat_up":"","stat_down":""}},"values":{"move":["Protect","Crunch","Destiny Bond","Ice Fang","Close Combat","Liquidation","Waterfall","Psychic Fangs","Ice Beam","Avalanche"],"held_item":["Sharpedonite","Focus Sash","Life Orb","Expert Belt","Lum Berry","Black Glasses","Mental Herb","Mystic Water","Quick Claw","Wacan Berry"],"teammate":["Garchomp","Mimikyu","Archaludon","Meowscarada","Metagross","Blaziken","Raichu","Glimmora","Hippowdon","Volcarona"],"stat_alignment":["Adamant","Jolly","Modest","Naughty","Naive","Lonely","Hasty","Rash","Mild","Timid"],"stat_points":["HP 2 / Atk 32 / Def 0 / SpA 0 / SpD 0 / Spe 32","HP 0 / Atk 32 / Def 2 / SpA 0 / SpD 0 / Spe 32","HP 0 / Atk 32 / Def 0 / SpA 0 / SpD 0 / Spe 32","HP 0 / Atk 32 / Def 0 / SpA 0 / SpD 2 / Spe 32","HP 2 / Atk 0 / Def 0 / SpA 32 / SpD 0 / Spe 32","HP 1 / Atk 32 / Def 1 / SpA 0 / SpD 0 / Spe 32","HP 0 / Atk 2 / Def 0 / SpA 32 / SpD 0 / Spe 32","HP 4 / Atk 32 / Def 0 / SpA 0 / SpD 0 / Spe 30"],"ability":["Speed Boost","Rough Skin"]},"rows":[{"pokemon":"Sharpedo","column_position":108,"position":108,"category":"move","rank":1,"name":"Protect","percentage":"83.6%","percentage_value":83.6,"stat_up":"","stat_down":""},{"pokemon":"Sharpedo","column_position":108,"position":108,"category":"move","rank":2,"name":"Crunch","percentage":"77.1%","percentage_value":77.1,"stat_up":"","stat_down":""},{"pokemon":"Sharpedo","column_position":108,"position":108,"category":"move","rank":3,"name":"Destiny Bond","percentage":"67.3%","percentage_value":67.3,"stat_up":"","stat_down":""},{"pokemon":"Sharpedo","column_position":108,"position":108,"category":"move","rank":4,"name":"Ice Fang","percentage":"35.9%","percentage_value":35.9,"stat_up":"","stat_down":""},{"pokemon":"Sharpedo","column_position":108,"position":108,"category":"move","rank":5,"name":"Close Combat","percentage":"31.1%","percentage_value":31.1,"stat_up":"","stat_down":""},{"pokemon":"Sharpedo","column_position":108,"position":108,"category":"move","rank":6,"name":"Liquidation","percentage":"17.9%","percentage_value":17.9,"stat_up":"","stat_down":""},{"pokemon":"Sharpedo","column_position":108,"position":108,"category":"move","rank":7,"name":"Waterfall","percentage":"15.3%","percentage_value":15.3,"stat_up":"","stat_down":""},{"pokemon":"Sharpedo","column_position":108,"position":108,"category":"move","rank":8,"name":"Psychic Fangs","percentage":"14.1%","percentage_value":14.1,"stat_up":"","stat_down":""},{"pokemon":"Sharpedo","column_position":108,"position":108,"category":"move","rank":9,"name":"Ice Beam","percentage":"9.4%","percentage_value":9.4,"stat_up":"","stat_down":""},{"pokemon":"Sharpedo","column_position":108,"position":108,"category":"move","rank":10,"name":"Avalanche","percentage":"7.1%","percentage_value":7.1,"stat_up":"","stat_down":""},{"pokemon":"Sharpedo","column_position":108,"position":108,"category":"held_item","rank":1,"name":"Sharpedonite","percentage":"50.4%","percentage_value":50.4,"stat_up":"","stat_down":""},{"pokemon":"Sharpedo","column_position":108,"position":108,"category":"held_item","rank":2,"name":"Focus Sash","percentage":"35.2%","percentage_value":35.2,"stat_up":"","stat_down":""},{"pokemon":"Sharpedo","column_position":108,"position":108,"category":"held_item","rank":3,"name":"Life Orb","percentage":"7.3%","percentage_value":7.3,"stat_up":"","stat_down":""},{"pokemon":"Sharpedo","column_position":108,"position":108,"category":"held_item","rank":4,"name":"Expert Belt","percentage":"1.0%","percentage_value":1,"stat_up":"","stat_down":""},{"pokemon":"Sharpedo","column_position":108,"position":108,"category":"held_item","rank":5,"name":"Lum Berry","percentage":"0.9%","percentage_value":0.9,"stat_up":"","stat_down":""},{"pokemon":"Sharpedo","column_position":108,"position":108,"category":"held_item","rank":6,"name":"Black Glasses","percentage":"0.8%","percentage_value":0.8,"stat_up":"","stat_down":""},{"pokemon":"Sharpedo","column_position":108,"position":108,"category":"held_item","rank":7,"name":"Mental Herb","percentage":"0.5%","percentage_value":0.5,"stat_up":"","stat_down":""},{"pokemon":"Sharpedo","column_position":108,"position":108,"category":"held_item","rank":8,"name":"Mystic Water","percentage":"0.4%","percentage_value":0.4,"stat_up":"","stat_down":""},{"pokemon":"Sharpedo","column_position":108,"position":108,"category":"held_item","rank":9,"name":"Quick Claw","percentage":"0.4%","percentage_value":0.4,"stat_up":"","stat_down":""},{"pokemon":"Sharpedo","column_position":108,"position":108,"category":"held_item","rank":10,"name":"Wacan Berry","percentage":"0.3%","percentage_value":0.3,"stat_up":"","stat_down":""},{"pokemon":"Sharpedo","column_position":108,"position":108,"category":"teammate","rank":1,"name":"Garchomp","percentage":"","percentage_value":null,"stat_up":"","stat_down":""},{"pokemon":"Sharpedo","column_position":108,"position":108,"category":"teammate","rank":2,"name":"Mimikyu","percentage":"","percentage_value":null,"stat_up":"","stat_down":""},{"pokemon":"Sharpedo","column_position":108,"position":108,"category":"teammate","rank":3,"name":"Archaludon","percentage":"","percentage_value":null,"stat_up":"","stat_down":""},{"pokemon":"Sharpedo","column_position":108,"position":108,"category":"teammate","rank":4,"name":"Meowscarada","percentage":"","percentage_value":null,"stat_up":"","stat_down":""},{"pokemon":"Sharpedo","column_position":108,"position":108,"category":"teammate","rank":5,"name":"Metagross","percentage":"","percentage_value":null,"stat_up":"","stat_down":""},{"pokemon":"Sharpedo","column_position":108,"position":108,"category":"teammate","rank":6,"name":"Blaziken","percentage":"","percentage_value":null,"stat_up":"","stat_down":""},{"pokemon":"Sharpedo","column_position":108,"position":108,"category":"teammate","rank":7,"name":"Raichu","percentage":"","percentage_value":null,"stat_up":"","stat_down":""},{"pokemon":"Sharpedo","column_position":108,"position":108,"category":"teammate","rank":8,"name":"Glimmora","percentage":"","percentage_value":null,"stat_up":"","stat_down":""},{"pokemon":"Sharpedo","column_position":108,"position":108,"category":"teammate","rank":9,"name":"Hippowdon","percentage":"","percentage_value":null,"stat_up":"","stat_down":""},{"pokemon":"Sharpedo","column_position":108,"position":108,"category":"teammate","rank":10,"name":"Volcarona","percentage":"","percentage_value":null,"stat_up":"","stat_down":""},{"pokemon":"Sharpedo","column_position":108,"position":108,"category":"stat_alignment","rank":1,"name":"Adamant","percentage":"60.9%","percentage_value":60.9,"stat_up":"Attack","stat_down":"Sp. Atk"},{"pokemon":"Sharpedo","column_position":108,"position":108,"category":"stat_alignment","rank":2,"name":"Jolly","percentage":"21.6%","percentage_value":21.6,"stat_up":"Speed","stat_down":"Sp. Atk"},{"pokemon":"Sharpedo","column_position":108,"position":108,"category":"stat_alignment","rank":3,"name":"Modest","percentage":"4.1%","percentage_value":4.1,"stat_up":"Sp. Atk","stat_down":"Attack"},{"pokemon":"Sharpedo","column_position":108,"position":108,"category":"stat_alignment","rank":4,"name":"Naughty","percentage":"2.9%","percentage_value":2.9,"stat_up":"Attack","stat_down":"Sp. Def"},{"pokemon":"Sharpedo","column_position":108,"position":108,"category":"stat_alignment","rank":5,"name":"Naive","percentage":"2.9%","percentage_value":2.9,"stat_up":"Speed","stat_down":"Sp. Def"},{"pokemon":"Sharpedo","column_position":108,"position":108,"category":"stat_alignment","rank":6,"name":"Lonely","percentage":"2.4%","percentage_value":2.4,"stat_up":"Attack","stat_down":"Defense"},{"pokemon":"Sharpedo","column_position":108,"position":108,"category":"stat_alignment","rank":7,"name":"Hasty","percentage":"1.6%","percentage_value":1.6,"stat_up":"Speed","stat_down":"Defense"},{"pokemon":"Sharpedo","column_position":108,"position":108,"category":"stat_alignment","rank":8,"name":"Rash","percentage":"1.6%","percentage_value":1.6,"stat_up":"Sp. Atk","stat_down":"Sp. Def"},{"pokemon":"Sharpedo","column_position":108,"position":108,"category":"stat_alignment","rank":9,"name":"Mild","percentage":"0.8%","percentage_value":0.8,"stat_up":"Sp. Atk","stat_down":"Defense"},{"pokemon":"Sharpedo","column_position":108,"position":108,"category":"stat_alignment","rank":10,"name":"Timid","percentage":"0.7%","percentage_value":0.7,"stat_up":"Speed","stat_down":"Attack"},{"pokemon":"Sharpedo","column_position":108,"position":108,"category":"stat_points","rank":1,"name":"","percentage":"58.7%","percentage_value":58.7,"stat_up":"","stat_down":"","hp_points":2,"attack_points":32,"defense_points":0,"sp_atk_points":0,"sp_def_points":0,"speed_points":32},{"pokemon":"Sharpedo","column_position":108,"position":108,"category":"stat_points","rank":2,"name":"","percentage":"5.9%","percentage_value":5.9,"stat_up":"","stat_down":"","hp_points":0,"attack_points":32,"defense_points":2,"sp_atk_points":0,"sp_def_points":0,"speed_points":32},{"pokemon":"Sharpedo","column_position":108,"position":108,"category":"stat_points","rank":3,"name":"","percentage":"4.7%","percentage_value":4.7,"stat_up":"","stat_down":"","hp_points":0,"attack_points":32,"defense_points":0,"sp_atk_points":0,"sp_def_points":0,"speed_points":32},{"pokemon":"Sharpedo","column_position":108,"position":108,"category":"stat_points","rank":4,"name":"","percentage":"4.5%","percentage_value":4.5,"stat_up":"","stat_down":"","hp_points":0,"attack_points":32,"defense_points":0,"sp_atk_points":0,"sp_def_points":2,"speed_points":32},{"pokemon":"Sharpedo","column_position":108,"position":108,"category":"stat_points","rank":5,"name":"","percentage":"3.7%","percentage_value":3.7,"stat_up":"","stat_down":"","hp_points":2,"attack_points":0,"defense_points":0,"sp_atk_points":32,"sp_def_points":0,"speed_points":32},{"pokemon":"Sharpedo","column_position":108,"position":108,"category":"stat_points","rank":6,"name":"","percentage":"1.4%","percentage_value":1.4,"stat_up":"","stat_down":"","hp_points":1,"attack_points":32,"defense_points":1,"sp_atk_points":0,"sp_def_points":0,"speed_points":32},{"pokemon":"Sharpedo","column_position":108,"position":108,"category":"stat_points","rank":7,"name":"","percentage":"1.3%","percentage_value":1.3,"stat_up":"","stat_down":"","hp_points":0,"attack_points":2,"defense_points":0,"sp_atk_points":32,"sp_def_points":0,"speed_points":32},{"pokemon":"Sharpedo","column_position":108,"position":108,"category":"stat_points","rank":8,"name":"","percentage":"1.2%","percentage_value":1.2,"stat_up":"","stat_down":"","hp_points":4,"attack_points":32,"defense_points":0,"sp_atk_points":0,"sp_def_points":0,"speed_points":30},{"pokemon":"Sharpedo","column_position":108,"position":108,"category":"ability","rank":1,"name":"Speed Boost","percentage":"99.4%","percentage_value":99.4,"stat_up":"","stat_down":""},{"pokemon":"Sharpedo","column_position":108,"position":108,"category":"ability","rank":2,"name":"Rough Skin","percentage":"0.6%","percentage_value":0.6,"stat_up":"","stat_down":""}]}}},"dailyBattleSummary":{"M4":{"16_07_2026":{"Doubles":{"top":{"move":{"pokemon":"Sharpedo","column_position":185,"position":185,"category":"move","rank":1,"name":"Protect","percentage":"96.4%","percentage_value":96.4,"stat_up":"","stat_down":""},"held_item":{"pokemon":"Sharpedo","column_position":185,"position":185,"category":"held_item","rank":1,"name":"Sharpedonite","percentage":"17.0%","percentage_value":17,"stat_up":"","stat_down":""},"teammate":{"pokemon":"Sharpedo","column_position":185,"position":185,"category":"teammate","rank":1,"name":"Sneasler","percentage":"","percentage_value":null,"stat_up":"","stat_down":""},"stat_alignment":{"pokemon":"Sharpedo","column_position":185,"position":185,"category":"stat_alignment","rank":1,"name":"Adamant","percentage":"81.3%","percentage_value":81.3,"stat_up":"Attack","stat_down":"Sp. Atk"},"stat_points":{"pokemon":"Sharpedo","column_position":185,"position":185,"category":"stat_points","rank":1,"name":"","percentage":"65.0%","percentage_value":65,"stat_up":"","stat_down":"","hp_points":2,"attack_points":32,"defense_points":0,"sp_atk_points":0,"sp_def_points":0,"speed_points":32},"ability":{"pokemon":"Sharpedo","column_position":185,"position":185,"category":"ability","rank":1,"name":"Speed Boost","percentage":"98.9%","percentage_value":98.9,"stat_up":"","stat_down":""}},"values":{"move":["Protect","Crunch","Ice Fang","Psychic Fangs","Liquidation","Close Combat","Destiny Bond","Waterfall","Rock Tomb","Poison Fang"],"held_item":["Sharpedonite","Focus Sash","Life Orb","Black Glasses","Mystic Water","Scope Lens","Quick Claw","Expert Belt","Sitrus Berry","Lum Berry"],"teammate":["Sneasler","Talonflame","Whimsicott","Sylveon","Kingambit","Farigiraf","Raichu","Incineroar","Milotic","Garchomp"],"stat_alignment":["Adamant","Jolly","Naive","Timid","Hasty","Naughty","Lonely","Modest","Brave","Bashful"],"stat_points":["HP 2 / Atk 32 / Def 0 / SpA 0 / SpD 0 / Spe 32","HP 0 / Atk 32 / Def 2 / SpA 0 / SpD 0 / Spe 32","HP 0 / Atk 32 / Def 0 / SpA 0 / SpD 2 / Spe 32","HP 0 / Atk 32 / Def 4 / SpA 0 / SpD 0 / Spe 30","HP 15 / Atk 32 / Def 0 / SpA 0 / SpD 0 / Spe 19","HP 14 / Atk 32 / Def 0 / SpA 0 / SpD 0 / Spe 20","HP 27 / Atk 30 / Def 0 / SpA 0 / SpD 0 / Spe 9","HP 0 / Atk 32 / Def 17 / SpA 0 / SpD 0 / Spe 17"],"ability":["Speed Boost","Rough Skin"]},"rows":[{"pokemon":"Sharpedo","column_position":185,"position":185,"category":"move","rank":1,"name":"Protect","percentage":"96.4%","percentage_value":96.4,"stat_up":"","stat_down":""},{"pokemon":"Sharpedo","column_position":185,"position":185,"category":"move","rank":2,"name":"Crunch","percentage":"95.6%","percentage_value":95.6,"stat_up":"","stat_down":""},{"pokemon":"Sharpedo","column_position":185,"position":185,"category":"move","rank":3,"name":"Ice Fang","percentage":"60.5%","percentage_value":60.5,"stat_up":"","stat_down":""},{"pokemon":"Sharpedo","column_position":185,"position":185,"category":"move","rank":4,"name":"Psychic Fangs","percentage":"59.8%","percentage_value":59.8,"stat_up":"","stat_down":""},{"pokemon":"Sharpedo","column_position":185,"position":185,"category":"move","rank":5,"name":"Liquidation","percentage":"27.5%","percentage_value":27.5,"stat_up":"","stat_down":""},{"pokemon":"Sharpedo","column_position":185,"position":185,"category":"move","rank":6,"name":"Close Combat","percentage":"11.6%","percentage_value":11.6,"stat_up":"","stat_down":""},{"pokemon":"Sharpedo","column_position":185,"position":185,"category":"move","rank":7,"name":"Destiny Bond","percentage":"11.0%","percentage_value":11,"stat_up":"","stat_down":""},{"pokemon":"Sharpedo","column_position":185,"position":185,"category":"move","rank":8,"name":"Waterfall","percentage":"9.1%","percentage_value":9.1,"stat_up":"","stat_down":""},{"pokemon":"Sharpedo","column_position":185,"position":185,"category":"move","rank":9,"name":"Rock Tomb","percentage":"5.4%","percentage_value":5.4,"stat_up":"","stat_down":""},{"pokemon":"Sharpedo","column_position":185,"position":185,"category":"move","rank":10,"name":"Poison Fang","percentage":"4.8%","percentage_value":4.8,"stat_up":"","stat_down":""},{"pokemon":"Sharpedo","column_position":185,"position":185,"category":"held_item","rank":1,"name":"Sharpedonite","percentage":"17.0%","percentage_value":17,"stat_up":"","stat_down":""},{"pokemon":"Sharpedo","column_position":185,"position":185,"category":"held_item","rank":2,"name":"Focus Sash","percentage":"13.3%","percentage_value":13.3,"stat_up":"","stat_down":""},{"pokemon":"Sharpedo","column_position":185,"position":185,"category":"held_item","rank":3,"name":"Life Orb","percentage":"3.9%","percentage_value":3.9,"stat_up":"","stat_down":""},{"pokemon":"Sharpedo","column_position":185,"position":185,"category":"held_item","rank":4,"name":"Black Glasses","percentage":"0.9%","percentage_value":0.9,"stat_up":"","stat_down":""},{"pokemon":"Sharpedo","column_position":185,"position":185,"category":"held_item","rank":5,"name":"Mystic Water","percentage":"0.9%","percentage_value":0.9,"stat_up":"","stat_down":""},{"pokemon":"Sharpedo","column_position":185,"position":185,"category":"held_item","rank":6,"name":"Scope Lens","percentage":"0.8%","percentage_value":0.8,"stat_up":"","stat_down":""},{"pokemon":"Sharpedo","column_position":185,"position":185,"category":"held_item","rank":7,"name":"Quick Claw","percentage":"0.8%","percentage_value":0.8,"stat_up":"","stat_down":""},{"pokemon":"Sharpedo","column_position":185,"position":185,"category":"held_item","rank":8,"name":"Expert Belt","percentage":"0.7%","percentage_value":0.7,"stat_up":"","stat_down":""},{"pokemon":"Sharpedo","column_position":185,"position":185,"category":"held_item","rank":9,"name":"Sitrus Berry","percentage":"0.2%","percentage_value":0.2,"stat_up":"","stat_down":""},{"pokemon":"Sharpedo","column_position":185,"position":185,"category":"held_item","rank":10,"name":"Lum Berry","percentage":"0.2%","percentage_value":0.2,"stat_up":"","stat_down":""},{"pokemon":"Sharpedo","column_position":185,"position":185,"category":"teammate","rank":1,"name":"Sneasler","percentage":"","percentage_value":null,"stat_up":"","stat_down":""},{"pokemon":"Sharpedo","column_position":185,"position":185,"category":"teammate","rank":2,"name":"Talonflame","percentage":"","percentage_value":null,"stat_up":"","stat_down":""},{"pokemon":"Sharpedo","column_position":185,"position":185,"category":"teammate","rank":3,"name":"Whimsicott","percentage":"","percentage_value":null,"stat_up":"","stat_down":""},{"pokemon":"Sharpedo","column_position":185,"position":185,"category":"teammate","rank":4,"name":"Sylveon","percentage":"","percentage_value":null,"stat_up":"","stat_down":""},{"pokemon":"Sharpedo","column_position":185,"position":185,"category":"teammate","rank":5,"name":"Kingambit","percentage":"","percentage_value":null,"stat_up":"","stat_down":""},{"pokemon":"Sharpedo","column_position":185,"position":185,"category":"teammate","rank":6,"name":"Farigiraf","percentage":"","percentage_value":null,"stat_up":"","stat_down":""},{"pokemon":"Sharpedo","column_position":185,"position":185,"category":"teammate","rank":7,"name":"Raichu","percentage":"","percentage_value":null,"stat_up":"","stat_down":""},{"pokemon":"Sharpedo","column_position":185,"position":185,"category":"teammate","rank":8,"name":"Incineroar","percentage":"","percentage_value":null,"stat_up":"","stat_down":""},{"pokemon":"Sharpedo","column_position":185,"position":185,"category":"teammate","rank":9,"name":"Milotic","percentage":"","percentage_value":null,"stat_up":"","stat_down":""},{"pokemon":"Sharpedo","column_position":185,"position":185,"category":"teammate","rank":10,"name":"Garchomp","percentage":"","percentage_value":null,"stat_up":"","stat_down":""},{"pokemon":"Sharpedo","column_position":185,"position":185,"category":"stat_alignment","rank":1,"name":"Adamant","percentage":"81.3%","percentage_value":81.3,"stat_up":"Attack","stat_down":"Sp. Atk"},{"pokemon":"Sharpedo","column_position":185,"position":185,"category":"stat_alignment","rank":2,"name":"Jolly","percentage":"13.6%","percentage_value":13.6,"stat_up":"Speed","stat_down":"Sp. Atk"},{"pokemon":"Sharpedo","column_position":185,"position":185,"category":"stat_alignment","rank":3,"name":"Naive","percentage":"1.4%","percentage_value":1.4,"stat_up":"Speed","stat_down":"Sp. Def"},{"pokemon":"Sharpedo","column_position":185,"position":185,"category":"stat_alignment","rank":4,"name":"Timid","percentage":"1.2%","percentage_value":1.2,"stat_up":"Speed","stat_down":"Attack"},{"pokemon":"Sharpedo","column_position":185,"position":185,"category":"stat_alignment","rank":5,"name":"Hasty","percentage":"0.8%","percentage_value":0.8,"stat_up":"Speed","stat_down":"Defense"},{"pokemon":"Sharpedo","column_position":185,"position":185,"category":"stat_alignment","rank":6,"name":"Naughty","percentage":"0.6%","percentage_value":0.6,"stat_up":"Attack","stat_down":"Sp. Def"},{"pokemon":"Sharpedo","column_position":185,"position":185,"category":"stat_alignment","rank":7,"name":"Lonely","percentage":"0.4%","percentage_value":0.4,"stat_up":"Attack","stat_down":"Defense"},{"pokemon":"Sharpedo","column_position":185,"position":185,"category":"stat_alignment","rank":8,"name":"Modest","percentage":"0.2%","percentage_value":0.2,"stat_up":"Sp. Atk","stat_down":"Attack"},{"pokemon":"Sharpedo","column_position":185,"position":185,"category":"stat_alignment","rank":9,"name":"Brave","percentage":"0.2%","percentage_value":0.2,"stat_up":"Attack","stat_down":"Speed"},{"pokemon":"Sharpedo","column_position":185,"position":185,"category":"stat_alignment","rank":10,"name":"Bashful","percentage":"0.1%","percentage_value":0.1,"stat_up":"","stat_down":""},{"pokemon":"Sharpedo","column_position":185,"position":185,"category":"stat_points","rank":1,"name":"","percentage":"65.0%","percentage_value":65,"stat_up":"","stat_down":"","hp_points":2,"attack_points":32,"defense_points":0,"sp_atk_points":0,"sp_def_points":0,"speed_points":32},{"pokemon":"Sharpedo","column_position":185,"position":185,"category":"stat_points","rank":2,"name":"","percentage":"3.3%","percentage_value":3.3,"stat_up":"","stat_down":"","hp_points":0,"attack_points":32,"defense_points":2,"sp_atk_points":0,"sp_def_points":0,"speed_points":32},{"pokemon":"Sharpedo","column_position":185,"position":185,"category":"stat_points","rank":3,"name":"","percentage":"3.2%","percentage_value":3.2,"stat_up":"","stat_down":"","hp_points":0,"attack_points":32,"defense_points":0,"sp_atk_points":0,"sp_def_points":2,"speed_points":32},{"pokemon":"Sharpedo","column_position":185,"position":185,"category":"stat_points","rank":4,"name":"","percentage":"2.7%","percentage_value":2.7,"stat_up":"","stat_down":"","hp_points":0,"attack_points":32,"defense_points":4,"sp_atk_points":0,"sp_def_points":0,"speed_points":30},{"pokemon":"Sharpedo","column_position":185,"position":185,"category":"stat_points","rank":5,"name":"","percentage":"2.5%","percentage_value":2.5,"stat_up":"","stat_down":"","hp_points":15,"attack_points":32,"defense_points":0,"sp_atk_points":0,"sp_def_points":0,"speed_points":19},{"pokemon":"Sharpedo","column_position":185,"position":185,"category":"stat_points","rank":6,"name":"","percentage":"1.6%","percentage_value":1.6,"stat_up":"","stat_down":"","hp_points":14,"attack_points":32,"defense_points":0,"sp_atk_points":0,"sp_def_points":0,"speed_points":20},{"pokemon":"Sharpedo","column_position":185,"position":185,"category":"stat_points","rank":7,"name":"","percentage":"1.6%","percentage_value":1.6,"stat_up":"","stat_down":"","hp_points":27,"attack_points":30,"defense_points":0,"sp_atk_points":0,"sp_def_points":0,"speed_points":9},{"pokemon":"Sharpedo","column_position":185,"position":185,"category":"stat_points","rank":8,"name":"","percentage":"1.5%","percentage_value":1.5,"stat_up":"","stat_down":"","hp_points":0,"attack_points":32,"defense_points":17,"sp_atk_points":0,"sp_def_points":0,"speed_points":17},{"pokemon":"Sharpedo","column_position":185,"position":185,"category":"ability","rank":1,"name":"Speed Boost","percentage":"98.9%","percentage_value":98.9,"stat_up":"","stat_down":""},{"pokemon":"Sharpedo","column_position":185,"position":185,"category":"ability","rank":2,"name":"Rough Skin","percentage":"1.1%","percentage_value":1.1,"stat_up":"","stat_down":""}]},"Singles":{"top":{"move":{"pokemon":"Sharpedo","column_position":108,"position":108,"category":"move","rank":1,"name":"Protect","percentage":"83.6%","percentage_value":83.6,"stat_up":"","stat_down":""},"held_item":{"pokemon":"Sharpedo","column_position":108,"position":108,"category":"held_item","rank":1,"name":"Sharpedonite","percentage":"50.4%","percentage_value":50.4,"stat_up":"","stat_down":""},"teammate":{"pokemon":"Sharpedo","column_position":108,"position":108,"category":"teammate","rank":1,"name":"Garchomp","percentage":"","percentage_value":null,"stat_up":"","stat_down":""},"stat_alignment":{"pokemon":"Sharpedo","column_position":108,"position":108,"category":"stat_alignment","rank":1,"name":"Adamant","percentage":"60.9%","percentage_value":60.9,"stat_up":"Attack","stat_down":"Sp. Atk"},"stat_points":{"pokemon":"Sharpedo","column_position":108,"position":108,"category":"stat_points","rank":1,"name":"","percentage":"58.7%","percentage_value":58.7,"stat_up":"","stat_down":"","hp_points":2,"attack_points":32,"defense_points":0,"sp_atk_points":0,"sp_def_points":0,"speed_points":32},"ability":{"pokemon":"Sharpedo","column_position":108,"position":108,"category":"ability","rank":1,"name":"Speed Boost","percentage":"99.4%","percentage_value":99.4,"stat_up":"","stat_down":""}},"values":{"move":["Protect","Crunch","Destiny Bond","Ice Fang","Close Combat","Liquidation","Waterfall","Psychic Fangs","Ice Beam","Avalanche"],"held_item":["Sharpedonite","Focus Sash","Life Orb","Expert Belt","Lum Berry","Black Glasses","Mental Herb","Mystic Water","Quick Claw","Wacan Berry"],"teammate":["Garchomp","Mimikyu","Archaludon","Meowscarada","Metagross","Blaziken","Raichu","Glimmora","Hippowdon","Volcarona"],"stat_alignment":["Adamant","Jolly","Modest","Naughty","Naive","Lonely","Hasty","Rash","Mild","Timid"],"stat_points":["HP 2 / Atk 32 / Def 0 / SpA 0 / SpD 0 / Spe 32","HP 0 / Atk 32 / Def 2 / SpA 0 / SpD 0 / Spe 32","HP 0 / Atk 32 / Def 0 / SpA 0 / SpD 0 / Spe 32","HP 0 / Atk 32 / Def 0 / SpA 0 / SpD 2 / Spe 32","HP 2 / Atk 0 / Def 0 / SpA 32 / SpD 0 / Spe 32","HP 1 / Atk 32 / Def 1 / SpA 0 / SpD 0 / Spe 32","HP 0 / Atk 2 / Def 0 / SpA 32 / SpD 0 / Spe 32","HP 4 / Atk 32 / Def 0 / SpA 0 / SpD 0 / Spe 30"],"ability":["Speed Boost","Rough Skin"]},"rows":[{"pokemon":"Sharpedo","column_position":108,"position":108,"category":"move","rank":1,"name":"Protect","percentage":"83.6%","percentage_value":83.6,"stat_up":"","stat_down":""},{"pokemon":"Sharpedo","column_position":108,"position":108,"category":"move","rank":2,"name":"Crunch","percentage":"77.1%","percentage_value":77.1,"stat_up":"","stat_down":""},{"pokemon":"Sharpedo","column_position":108,"position":108,"category":"move","rank":3,"name":"Destiny Bond","percentage":"67.3%","percentage_value":67.3,"stat_up":"","stat_down":""},{"pokemon":"Sharpedo","column_position":108,"position":108,"category":"move","rank":4,"name":"Ice Fang","percentage":"35.9%","percentage_value":35.9,"stat_up":"","stat_down":""},{"pokemon":"Sharpedo","column_position":108,"position":108,"category":"move","rank":5,"name":"Close Combat","percentage":"31.1%","percentage_value":31.1,"stat_up":"","stat_down":""},{"pokemon":"Sharpedo","column_position":108,"position":108,"category":"move","rank":6,"name":"Liquidation","percentage":"17.9%","percentage_value":17.9,"stat_up":"","stat_down":""},{"pokemon":"Sharpedo","column_position":108,"position":108,"category":"move","rank":7,"name":"Waterfall","percentage":"15.3%","percentage_value":15.3,"stat_up":"","stat_down":""},{"pokemon":"Sharpedo","column_position":108,"position":108,"category":"move","rank":8,"name":"Psychic Fangs","percentage":"14.1%","percentage_value":14.1,"stat_up":"","stat_down":""},{"pokemon":"Sharpedo","column_position":108,"position":108,"category":"move","rank":9,"name":"Ice Beam","percentage":"9.4%","percentage_value":9.4,"stat_up":"","stat_down":""},{"pokemon":"Sharpedo","column_position":108,"position":108,"category":"move","rank":10,"name":"Avalanche","percentage":"7.1%","percentage_value":7.1,"stat_up":"","stat_down":""},{"pokemon":"Sharpedo","column_position":108,"position":108,"category":"held_item","rank":1,"name":"Sharpedonite","percentage":"50.4%","percentage_value":50.4,"stat_up":"","stat_down":""},{"pokemon":"Sharpedo","column_position":108,"position":108,"category":"held_item","rank":2,"name":"Focus Sash","percentage":"35.2%","percentage_value":35.2,"stat_up":"","stat_down":""},{"pokemon":"Sharpedo","column_position":108,"position":108,"category":"held_item","rank":3,"name":"Life Orb","percentage":"7.3%","percentage_value":7.3,"stat_up":"","stat_down":""},{"pokemon":"Sharpedo","column_position":108,"position":108,"category":"held_item","rank":4,"name":"Expert Belt","percentage":"1.0%","percentage_value":1,"stat_up":"","stat_down":""},{"pokemon":"Sharpedo","column_position":108,"position":108,"category":"held_item","rank":5,"name":"Lum Berry","percentage":"0.9%","percentage_value":0.9,"stat_up":"","stat_down":""},{"pokemon":"Sharpedo","column_position":108,"position":108,"category":"held_item","rank":6,"name":"Black Glasses","percentage":"0.8%","percentage_value":0.8,"stat_up":"","stat_down":""},{"pokemon":"Sharpedo","column_position":108,"position":108,"category":"held_item","rank":7,"name":"Mental Herb","percentage":"0.5%","percentage_value":0.5,"stat_up":"","stat_down":""},{"pokemon":"Sharpedo","column_position":108,"position":108,"category":"held_item","rank":8,"name":"Mystic Water","percentage":"0.4%","percentage_value":0.4,"stat_up":"","stat_down":""},{"pokemon":"Sharpedo","column_position":108,"position":108,"category":"held_item","rank":9,"name":"Quick Claw","percentage":"0.4%","percentage_value":0.4,"stat_up":"","stat_down":""},{"pokemon":"Sharpedo","column_position":108,"position":108,"category":"held_item","rank":10,"name":"Wacan Berry","percentage":"0.3%","percentage_value":0.3,"stat_up":"","stat_down":""},{"pokemon":"Sharpedo","column_position":108,"position":108,"category":"teammate","rank":1,"name":"Garchomp","percentage":"","percentage_value":null,"stat_up":"","stat_down":""},{"pokemon":"Sharpedo","column_position":108,"position":108,"category":"teammate","rank":2,"name":"Mimikyu","percentage":"","percentage_value":null,"stat_up":"","stat_down":""},{"pokemon":"Sharpedo","column_position":108,"position":108,"category":"teammate","rank":3,"name":"Archaludon","percentage":"","percentage_value":null,"stat_up":"","stat_down":""},{"pokemon":"Sharpedo","column_position":108,"position":108,"category":"teammate","rank":4,"name":"Meowscarada","percentage":"","percentage_value":null,"stat_up":"","stat_down":""},{"pokemon":"Sharpedo","column_position":108,"position":108,"category":"teammate","rank":5,"name":"Metagross","percentage":"","percentage_value":null,"stat_up":"","stat_down":""},{"pokemon":"Sharpedo","column_position":108,"position":108,"category":"teammate","rank":6,"name":"Blaziken","percentage":"","percentage_value":null,"stat_up":"","stat_down":""},{"pokemon":"Sharpedo","column_position":108,"position":108,"category":"teammate","rank":7,"name":"Raichu","percentage":"","percentage_value":null,"stat_up":"","stat_down":""},{"pokemon":"Sharpedo","column_position":108,"position":108,"category":"teammate","rank":8,"name":"Glimmora","percentage":"","percentage_value":null,"stat_up":"","stat_down":""},{"pokemon":"Sharpedo","column_position":108,"position":108,"category":"teammate","rank":9,"name":"Hippowdon","percentage":"","percentage_value":null,"stat_up":"","stat_down":""},{"pokemon":"Sharpedo","column_position":108,"position":108,"category":"teammate","rank":10,"name":"Volcarona","percentage":"","percentage_value":null,"stat_up":"","stat_down":""},{"pokemon":"Sharpedo","column_position":108,"position":108,"category":"stat_alignment","rank":1,"name":"Adamant","percentage":"60.9%","percentage_value":60.9,"stat_up":"Attack","stat_down":"Sp. Atk"},{"pokemon":"Sharpedo","column_position":108,"position":108,"category":"stat_alignment","rank":2,"name":"Jolly","percentage":"21.6%","percentage_value":21.6,"stat_up":"Speed","stat_down":"Sp. Atk"},{"pokemon":"Sharpedo","column_position":108,"position":108,"category":"stat_alignment","rank":3,"name":"Modest","percentage":"4.1%","percentage_value":4.1,"stat_up":"Sp. Atk","stat_down":"Attack"},{"pokemon":"Sharpedo","column_position":108,"position":108,"category":"stat_alignment","rank":4,"name":"Naughty","percentage":"2.9%","percentage_value":2.9,"stat_up":"Attack","stat_down":"Sp. Def"},{"pokemon":"Sharpedo","column_position":108,"position":108,"category":"stat_alignment","rank":5,"name":"Naive","percentage":"2.9%","percentage_value":2.9,"stat_up":"Speed","stat_down":"Sp. Def"},{"pokemon":"Sharpedo","column_position":108,"position":108,"category":"stat_alignment","rank":6,"name":"Lonely","percentage":"2.4%","percentage_value":2.4,"stat_up":"Attack","stat_down":"Defense"},{"pokemon":"Sharpedo","column_position":108,"position":108,"category":"stat_alignment","rank":7,"name":"Hasty","percentage":"1.6%","percentage_value":1.6,"stat_up":"Speed","stat_down":"Defense"},{"pokemon":"Sharpedo","column_position":108,"position":108,"category":"stat_alignment","rank":8,"name":"Rash","percentage":"1.6%","percentage_value":1.6,"stat_up":"Sp. Atk","stat_down":"Sp. Def"},{"pokemon":"Sharpedo","column_position":108,"position":108,"category":"stat_alignment","rank":9,"name":"Mild","percentage":"0.8%","percentage_value":0.8,"stat_up":"Sp. Atk","stat_down":"Defense"},{"pokemon":"Sharpedo","column_position":108,"position":108,"category":"stat_alignment","rank":10,"name":"Timid","percentage":"0.7%","percentage_value":0.7,"stat_up":"Speed","stat_down":"Attack"},{"pokemon":"Sharpedo","column_position":108,"position":108,"category":"stat_points","rank":1,"name":"","percentage":"58.7%","percentage_value":58.7,"stat_up":"","stat_down":"","hp_points":2,"attack_points":32,"defense_points":0,"sp_atk_points":0,"sp_def_points":0,"speed_points":32},{"pokemon":"Sharpedo","column_position":108,"position":108,"category":"stat_points","rank":2,"name":"","percentage":"5.9%","percentage_value":5.9,"stat_up":"","stat_down":"","hp_points":0,"attack_points":32,"defense_points":2,"sp_atk_points":0,"sp_def_points":0,"speed_points":32},{"pokemon":"Sharpedo","column_position":108,"position":108,"category":"stat_points","rank":3,"name":"","percentage":"4.7%","percentage_value":4.7,"stat_up":"","stat_down":"","hp_points":0,"attack_points":32,"defense_points":0,"sp_atk_points":0,"sp_def_points":0,"speed_points":32},{"pokemon":"Sharpedo","column_position":108,"position":108,"category":"stat_points","rank":4,"name":"","percentage":"4.5%","percentage_value":4.5,"stat_up":"","stat_down":"","hp_points":0,"attack_points":32,"defense_points":0,"sp_atk_points":0,"sp_def_points":2,"speed_points":32},{"pokemon":"Sharpedo","column_position":108,"position":108,"category":"stat_points","rank":5,"name":"","percentage":"3.7%","percentage_value":3.7,"stat_up":"","stat_down":"","hp_points":2,"attack_points":0,"defense_points":0,"sp_atk_points":32,"sp_def_points":0,"speed_points":32},{"pokemon":"Sharpedo","column_position":108,"position":108,"category":"stat_points","rank":6,"name":"","percentage":"1.4%","percentage_value":1.4,"stat_up":"","stat_down":"","hp_points":1,"attack_points":32,"defense_points":1,"sp_atk_points":0,"sp_def_points":0,"speed_points":32},{"pokemon":"Sharpedo","column_position":108,"position":108,"category":"stat_points","rank":7,"name":"","percentage":"1.3%","percentage_value":1.3,"stat_up":"","stat_down":"","hp_points":0,"attack_points":2,"defense_points":0,"sp_atk_points":32,"sp_def_points":0,"speed_points":32},{"pokemon":"Sharpedo","column_position":108,"position":108,"category":"stat_points","rank":8,"name":"","percentage":"1.2%","percentage_value":1.2,"stat_up":"","stat_down":"","hp_points":4,"attack_points":32,"defense_points":0,"sp_atk_points":0,"sp_def_points":0,"speed_points":30},{"pokemon":"Sharpedo","column_position":108,"position":108,"category":"ability","rank":1,"name":"Speed Boost","percentage":"99.4%","percentage_value":99.4,"stat_up":"","stat_down":""},{"pokemon":"Sharpedo","column_position":108,"position":108,"category":"ability","rank":2,"name":"Rough Skin","percentage":"0.6%","percentage_value":0.6,"stat_up":"","stat_down":""}]}}}}}}
